{
  "gitSyncId": "67d3b85e655e152c1c92db11_02903190-d5a8-4b69-adca-b408aec67141",
  "id": "Investors_utils.createInvestor",
  "pluginId": "js-plugin",
  "pluginType": "JS",
  "unpublishedAction": {
    "actionConfiguration": {
      "encodeParamsToggle": true,
      "jsArguments": [],
      "paginationType": "NONE",
      "timeoutInMillisecond": 10000
    },
    "collectionId": "Investors_utils",
    "confirmBeforeExecute": false,
    "datasource": {
      "isAutoGenerated": false,
      "name": "UNUSED_DATASOURCE",
      "pluginId": "js-plugin"
    },
    "dynamicBindingPathList": [
      {
        "key": "body"
      }
    ],
    "executeOnLoad": false,
    "fullyQualifiedName": "utils.createInvestor",
    "name": "createInvestor",
    "pageId": "Investors",
    "userSetOnLoad": false
  }
}